CHANGELOG.md
LICENSE.Apache.v2
LICENSE.GPL.v2
MANIFEST.in
README.license.md
README.rst
VERSION
setup.cfg
setup.py
pr2modules/__init__.py
pr2modules/common.py
pr2modules/conntrack.py
pr2modules/devlink.py
pr2modules/iwutil.py
pr2modules/proxy.py
pr2modules/bsd/__init__.py
pr2modules/bsd/util.py
pr2modules/bsd/pf_route/__init__.py
pr2modules/bsd/pf_route/freebsd.py
pr2modules/bsd/pf_route/openbsd.py
pr2modules/bsd/rtmsocket/__init__.py
pr2modules/bsd/rtmsocket/freebsd.py
pr2modules/bsd/rtmsocket/openbsd.py
pr2modules/config/__init__.py
pr2modules/config/asyncio.py
pr2modules/config/eventlet.py
pr2modules/config/log.py
pr2modules/config/test_platform.py
pr2modules/config/version.py
pr2modules/inotify/__init__.py
pr2modules/inotify/inotify_fd.py
pr2modules/inotify/inotify_msg.py
pr2modules/iproute/__init__.py
pr2modules/iproute/bsd.py
pr2modules/iproute/linux.py
pr2modules/iproute/req.py
pr2modules/iproute/windows.py
pr2modules/netlink/__init__.py
pr2modules/netlink/exceptions.py
pr2modules/netlink/nlsocket.py
pr2modules/netlink/devlink/__init__.py
pr2modules/netlink/diag/__init__.py
pr2modules/netlink/diag/ss2.py
pr2modules/netlink/event/__init__.py
pr2modules/netlink/event/acpi_event.py
pr2modules/netlink/event/dquot.py
pr2modules/netlink/event/thermal_event.py
pr2modules/netlink/generic/__init__.py
pr2modules/netlink/generic/ethtool.py
pr2modules/netlink/generic/l2tp.py
pr2modules/netlink/generic/mptcp.py
pr2modules/netlink/generic/wireguard.py
pr2modules/netlink/ipq/__init__.py
pr2modules/netlink/nfnetlink/__init__.py
pr2modules/netlink/nfnetlink/ipset.py
pr2modules/netlink/nfnetlink/nfctsocket.py
pr2modules/netlink/nfnetlink/nftsocket.py
pr2modules/netlink/nl80211/__init__.py
pr2modules/netlink/rtnl/__init__.py
pr2modules/netlink/rtnl/errmsg.py
pr2modules/netlink/rtnl/fibmsg.py
pr2modules/netlink/rtnl/ifaddrmsg.py
pr2modules/netlink/rtnl/ifstatsmsg.py
pr2modules/netlink/rtnl/iprsocket.py
pr2modules/netlink/rtnl/iw_event.py
pr2modules/netlink/rtnl/marshal.py
pyroute2.core.egg-info/PKG-INFO
pyroute2.core.egg-info/SOURCES.txt
pyroute2.core.egg-info/dependency_links.txt
pyroute2.core.egg-info/entry_points.txt
pyroute2.core.egg-info/namespace_packages.txt
pyroute2.core.egg-info/top_level.txt